ipybus/__init__.py
ipybus/_version.py
ipybus/base_widget.py
ipybus/labextension/package.json
ipybus/labextension/static/261.63b2d786d275cedc07f4.js
ipybus/labextension/static/486.394206e73c30e3ad6156.js
ipybus/labextension/static/486.394206e73c30e3ad6156.js.LICENSE.txt
ipybus/labextension/static/568.7eb2b4f2f5ab791b9a83.js
ipybus/labextension/static/remoteEntry.fdb13a5f6cf0cb50ec72.js
ipybus/labextension/static/style.js
ipybus/labextension/static/third-party-licenses.json
ipybus/nbextension/extension.js
ipybus/nbextension/index.js
ipybus/nbextension/index.js.LICENSE.txt
ipybus-0.1.2rc0.data/data/etc/jupyter/nbconfig/notebook.d/ipybus.json
ipybus-0.1.2rc0.data/data/share/jupyter/labextensions/ipybus/install.json
ipybus-0.1.2rc0.data/data/share/jupyter/labextensions/ipybus/package.json
ipybus-0.1.2rc0.data/data/share/jupyter/labextensions/ipybus/static/261.63b2d786d275cedc07f4.js
ipybus-0.1.2rc0.data/data/share/jupyter/labextensions/ipybus/static/486.394206e73c30e3ad6156.js
ipybus-0.1.2rc0.data/data/share/jupyter/labextensions/ipybus/static/486.394206e73c30e3ad6156.js.LICENSE.txt
ipybus-0.1.2rc0.data/data/share/jupyter/labextensions/ipybus/static/568.7eb2b4f2f5ab791b9a83.js
ipybus-0.1.2rc0.data/data/share/jupyter/labextensions/ipybus/static/remoteEntry.fdb13a5f6cf0cb50ec72.js
ipybus-0.1.2rc0.data/data/share/jupyter/labextensions/ipybus/static/style.js
ipybus-0.1.2rc0.data/data/share/jupyter/labextensions/ipybus/static/third-party-licenses.json
ipybus-0.1.2rc0.data/data/share/jupyter/nbextensions/ipybus/extension.js
ipybus-0.1.2rc0.data/data/share/jupyter/nbextensions/ipybus/index.js
ipybus-0.1.2rc0.data/data/share/jupyter/nbextensions/ipybus/index.js.LICENSE.txt
ipybus-0.1.2rc0.dist-info/METADATA
ipybus-0.1.2rc0.dist-info/WHEEL
ipybus-0.1.2rc0.dist-info/top_level.txt
ipybus-0.1.2rc0.dist-info/RECORD
